bareos_restapi/VERSION.txt
bareos_restapi/__init__.py
bareos_restapi/api.ini.example
bareos_restapi/metatags.yaml
bareos_restapi/models.py
bareos_restapi/openapi.json
bareos_restapi-25.0.1.dist-info/licenses/LICENSE
bareos_restapi-25.0.1.dist-info/METADATA
bareos_restapi-25.0.1.dist-info/WHEEL
bareos_restapi-25.0.1.dist-info/top_level.txt
bareos_restapi-25.0.1.dist-info/RECORD
