Metadata-Version: 2.4
Name: bareos-restapi
Version: 25.0.1
Summary: REST API for Bareos console access.
Home-page: https://github.com/bareos/bareos/
Author: Bareos Team
Author-email: packager@bareos.com
License: AGPLv3
Keywords: bareos,REST API
Classifier: Development Status :: 3 - Alpha
Classifier: License :: OSI Approved :: GNU Affero General Public License v3
Classifier: Operating System :: OS Independent
Classifier: Programming Language :: Python
Classifier: Topic :: System :: Archiving :: Backup
Requires-Python: >=3.6
License-File: LICENSE
Requires-Dist: fastapi
Requires-Dist: packaging
Requires-Dist: passlib
Requires-Dist: pydantic
Requires-Dist: python-bareos
Requires-Dist: python-jose
Requires-Dist: python-multipart
Requires-Dist: pyyaml
Requires-Dist: uvicorn
Dynamic: author
Dynamic: author-email
Dynamic: classifier
Dynamic: description
Dynamic: description-content-type
Dynamic: home-page
Dynamic: keywords
Dynamic: license
Dynamic: license-file
Dynamic: requires-dist
Dynamic: requires-python
Dynamic: summary
